{
  "version": "7",
  "dialect": "postgresql",
  "entries": [
    {
      "idx": 0,
      "version": "7",
      "when": 1731805343606,
      "tag": "0000_nosy_invaders",
      "breakpoints": true
    },
    {
      "idx": 1,
      "version": "7",
      "when": 1731805516400,
      "tag": "0001_perfect_gambit",
      "breakpoints": true
    },
    {
      "idx": 2,
      "version": "7",
      "when": 1731862139337,
      "tag": "0002_far_wolfsbane",
      "breakpoints": true
    },
    {
      "idx": 3,
      "version": "7",
      "when": 1731874236007,
      "tag": "0003_busy_talon",
      "breakpoints": true
    }
  ]
}